missing_diff_lines/__init__.py
missing_diff_lines/missing_diff_lines.py
missing_diff_lines-0.0.4.dist-info/LICENSE
missing_diff_lines-0.0.4.dist-info/METADATA
missing_diff_lines-0.0.4.dist-info/WHEEL
missing_diff_lines-0.0.4.dist-info/top_level.txt
missing_diff_lines-0.0.4.dist-info/RECORD
