Metadata-Version: 2.1
Name: missing-diff-lines
Version: 0.0.4
Summary: Creates a set of all lines that have no test coverage in the current git diff
Home-page: https://github.com/tom-010/missing_diff_lines
Author: Thomas Deniffel
Author-email: tdeniffel@gmail.com
License: Apache2
Platform: UNKNOWN
Classifier: Development Status :: 4 - Beta
Classifier: Intended Audience :: Developers
Classifier: Programming Language :: Python
Classifier: Programming Language :: Python :: 3 :: Only
Classifier: Programming Language :: Python :: 3.6
Classifier: Programming Language :: Python :: 3.7
Requires-Python: >=3
Requires-Dist: GitPython
Requires-Dist: coverage
